Workbook

Sheet Cover
A1: Britannia Industries Ltd (NSE: BRITANNIA) - Three-statement model and DCF
A2: Consolidated financials, Rs crore, fiscal year ending 31 March. Prepared 19-Oct-2026. Educational / portfolio project - not investment advice.
A4: KEY OUTPUTS
A5: Active scenario (change on Assumptions sheet) | B5: =Assumptions!C27 -> Base
A6: DCF value per share (Rs) | B6: =DCF!B61 -> 2692.1995
A7: Current share price (Rs) | B7: =Assumptions!$B$37 -> 4764
A8: DCF value vs current price | B8: =DCF!B63 -> -0.43488675
A9: WACC | B9: =DCF!B17 -> 0.1034752
A10: Terminal growth used | B10: =DCF!B18 -> 0.055
A11: Terminal growth implied by current price | B11: =DCF!B67 -> 0.080975027
A12: Terminal value as % of EV | B12: =DCF!B48 -> 0.66439575
A13: Market EV / EBITDA FY27E | B13: =DCF!B69 -> 28.366928
A14: Market P/E FY27E | B14: =DCF!B72 -> 40.791814
A16: VALUATION RANGE SUMMARY (Rs per share) | B16: Low | C16: High
A17: DCF (WACC +/- 0.5%, terminal growth +/- 0.5%) | B17: =Sensitivity!B28 -> 2308.7845 | C17: =Sensitivity!B29 -> 3270.5233
A18: Peer P/E x Britannia TTM EPS (low to high) | B18: =Comps!B20 -> 3472.4932 | C18: =Comps!D20 -> 5874.6974
A19: 52-week trading range | B19: =Assumptions!$B$47 -> 4734 | C19: =Assumptions!$B$48 -> 6271
A21: MODEL INTEGRITY CHECKS
A22: Historical statements tie to reported totals | B22: =Historical!B147 -> OK
A23: Balance sheet balances in every year (hist. + forecast) | B23: =IF(SUMPRODUCT(ABS(Model!B48:N48))<0.05,"OK","ERROR") -> OK
A24: Sensitivity centre cell equals DCF value | B24: =Sensitivity!B27 -> OK
A25: Forecast closing cash equals balance sheet cash | B25: =IF(SUMPRODUCT(ABS(Model!E71:N71-Model!E36:N36))<0.05,"OK","ERROR") -> OK
A27: HOW THE WORKBOOK IS ORGANISED
A28: Assumptions - every driver, scenario switch and market input (blue cells). Change these and everything flows through.
A29: Historical - FY24A-FY26A consolidated statements typed in from Britannia audited results, with tie-outs to reported totals.
A30: Model - income statement, balance sheet and cash flow, linked: net profit -> equity, working-capital and capex -> cash, cash -> balance sheet.
A31: DCF - WACC, unlevered free cash flow (10 years), terminal value, equity bridge, reverse DCF and implied multiples.
A32: Sensitivity - value per share across WACC and terminal growth. Comps - peer P/E cross-check.
A34: COLOUR CODE
A35: Blue text = hard-coded input
A36: Black text = formula
A37: Green text = link to another sheet
A38: Yellow fill = key assumption / headline output
A40: SOURCES
... A50: Forecast cash flow is a simplified indirect build (interest inside net profit); historical cash flows are shown as reported.

Sheet Assumptions
A1: Assumptions and drivers
A2: All forecast drivers live here. Blue = input (edit these). FY24A-FY26A columns show actual ratios for reference.
A4: Driver | B4: FY24A | C4: FY25A | D4: FY26A | E4: FY27E | F4: FY28E | G4: FY29E | H4: FY30E | I4: FY31E | J4: FY32E | K4: FY33E | L4: FY34E | M4: FY35E | N4: FY36E | O4: Basis / source
A5: Sale of goods growth - BASE case (YoY) | C5: =Model!C6/Model!B6-1 -> 0.059760513 | D5: =Model!D6/Model!C6-1 -> 0.075459851 | E5: 0.09 | F5: 0.09 | G5: 0.085 | H5: 0.08 | I5: 0.08 | J5: 0.075 | K5: 0.07 | L5: 0.065 | M5: 0.06 | N5: 0.055 | O5: Assumption. FY26A +7.5%. Fades toward terminal growth. Scenario adjustment (below) is added on top. Broker FY27E-28E growth is c.11%.
A6: Other operating revenues (% of sale of goods) | B6: =Model!B7/Model!B6 -> 0.013481033 | C6: =Model!C7/Model!C6 -> 0.023247764 | D6: =Model!D7/Model!D6 -> 0.01555715 | E6: 0.016 | F6: 0.016 | G6: 0.016 | H6: 0.016 | I6: 0.016 | J6: 0.016 | K6: 0.016 | L6: 0.016 | M6: 0.016 | N6: 0.016 | O6: Assumption = FY26A level.
A7: COGS (% of sale of goods) - BASE case | B7: =Model!B9/Model!B6 -> 0.57366793 | C7: =Model!C9/Model!C6 -> 0.60473555 | D7: =Model!D9/Model!D6 -> 0.59034659 | E7: 0.588 | F7: 0.586 | G7: 0.585 | H7: 0.585 | I7: 0.585 | J7: 0.585 | K7: 0.585 | L7: 0.585 | M7: 0.585 | N7: 0.585 | O7: Assumption. FY26A 59.0%; modest mix / premiumisation benefit, then flat. Scenario adjustment added on top.
A8: Employee cost (% of total revenue) | B8: =Model!B12/Model!B8 -> 0.042261828 | C8: =Model!C12/Model!C8 -> 0.039268961 | D8: =Model!D12/Model!D8 -> 0.043014705 | E8: 0.042 | F8: 0.042 | G8: 0.042 | H8: 0.042 | I8: 0.042 | J8: 0.042 | K8: 0.042 | L8: 0.042 | M8: 0.042 | N8: 0.042 | O8: Assumption. FY26A 4.3% incl. one-off labour-code charge.
A9: Other expenses (% of total revenue) | B9: =Model!B13/Model!B8 -> 0.2026743 | C9: =Model!C13/Model!C8 -> 0.19210519 | D9: =Model!D13/Model!D8 -> 0.19060976 | E9: 0.19 | F9: 0.19 | G9: 0.19 | H9: 0.19 | I9: 0.19 | J9: 0.19 | K9: 0.19 | L9: 0.19 | M9: 0.19 | N9: 0.19 | O9: Assumption. FY26A 19.1%.
A10: D&A (% of opening net fixed assets) | C10: =Model!C16/Model!B33 -> 0.10590534 | D10: =Model!D16/Model!C33 -> 0.11253926 | E10: 0.11 | F10: 0.11 | G10: 0.11 | H10: 0.11 | I10: 0.11 | J10: 0.11 | K10: 0.11 | L10: 0.11 | M10: 0.11 | N10: 0.11 | O10: Assumption. FY26A 11.3%.
A11: Capex (% of total revenue) | B11: =-Model!B63/Model!B8 -> 0.032969235 | C11: =-Model!C63/Model!C8 -> 0.02089154 | D11: =-Model!D63/Model!D8 -> 0.010733835 | E11: 0.02 | F11: 0.02 | G11: 0.02 | H11: 0.02 | I11: 0.02 | J11: 0.02 | K11: 0.02 | L11: 0.02 | M11: 0.02 | N11: 0.02 | O11: Assumption. FY24A 3.3%, FY25A 2.1%, FY26A 1.1% (below normal).
A12: Other income yield (% of opening cash + investments + other treasury) | C12: =Model!C18/(Model!B35+Model!B36+Model!B37) -> 0.07144093 | D12: =Model!D18/(Model!C35+Model!C36+Model!C37) -> 0.080897992 | E12: 0.07 | F12: 0.07 | G12: 0.07 | H12: 0.07 | I12: 0.07 | J12: 0.07 | K12: 0.07 | L12: 0.07 | M12: 0.07 | N12: 0.07 | O12: Assumption. FY25A 7.1%, FY26A 8.1% (incl. fair-value gains).
A13: Finance cost rate (% of opening borrowings) | C13: =Model!C19/Model!B45 -> 0.067216798 | D13: =Model!D19/Model!C45 -> 0.090460566 | E13: 0.08 | F13: 0.08 | G13: 0.08 | H13: 0.08 | I13: 0.08 | J13: 0.08 | K13: 0.08 | L13: 0.08 | M13: 0.08 | N13: 0.08 | O13: Assumption.
A14: Share of profit / (loss) of associates (Rs crore) | B14: =Model!B20 -> -3.19 | C14: =Model!C20 -> -10.74 | D14: =Model!D20 -> -30.09 | E14: -15 | F14: -15 | G14: -15 | H14: -15 | I14: -15 | J14: -15 | K14: -15 | L14: -15 | M14: -15 | N14: -15 | O14: Assumption. FY25A -10.7, FY26A -30.1.
A15: Effective tax rate (% of PBT) | B15: =Model!B23/Model!B22 -> 0.26746457 | C15: =Model!C23/Model!C22 -> 0.25583191 | D15: =Model!D23/Model!D22 -> 0.22858628 | E15: 0.252 | F15: 0.252 | G15: 0.252 | H15: 0.252 | I15: 0.252 | J15: 0.252 | K15: 0.252 | L15: 0.252 | M15: 0.252 | N15: 0.252 | O15: Assumption = c.25.2% statutory rate for Indian companies. FY26A 22.9% was flattered by a Rs 95 cr one-off provision reversal.
A16: Non-controlling interest in profit (Rs crore) | B16: =Model!B25 -> -5.59 | C16: =Model!C25 -> -0.87 | D16: =Model!D25 -> 3.52 | E16: 0 | F16: 0 | G16: 0 | H16: 0 | I16: 0 | J16: 0 | K16: 0 | L16: 0 | M16: 0 | N16: 0 | O16: Assumption (immaterial).
A17: Inventory days (on COGS) | B17: =Model!B38/Model!B9*365 -> 45.421822 | C17: =Model!C38/Model!C9*365 -> 42.561677 | D17: =Model!D38/Model!D9*365 -> 44.127346 | E17: 44 | F17: 44 | G17: 44 | H17: 44 | I17: 44 | J17: 44 | K17: 44 | L17: 44 | M17: 44 | N17: 44 | O17: Assumption = FY26A.
A18: Receivable days (on total revenue) | B18: =Model!B39/Model!B8*365 -> 8.5612224 | C18: =Model!C39/Model!C8*365 -> 9.1258798 | D18: =Model!D39/Model!D8*365 -> 8.9424246 | E18: 9 | F18: 9 | G18: 9 | H18: 9 | I18: 9 | J18: 9 | K18: 9 | L18: 9 | M18: 9 | N18: 9 | O18: Assumption.
A19: Payable days (on COGS + other expenses) | B19: =Model!B43/(Model!B9+Model!B13)*365 -> 46.081967 | C19: =Model!C43/(Model!C9+Model!C13)*365 -> 45.517553 | D19: =Model!D43/(Model!D9+Model!D13)*365 -> 46.822214 | E19: 46.5 | F19: 46.5 | G19: 46.5 | H19: 46.5 | I19: 46.5 | J19: 46.5 | K19: 46.5 | L19: 46.5 | M19: 46.5 | N19: 46.5 | O19: Assumption.
A20: Other operating assets (% of total revenue) | B20: =Model!B40/Model!B8 -> 0.051717218 | C20: =Model!C40/Model!C8 -> 0.050578871 | D20: =Model!D40/Model!D8 -> 0.050943029 | E20: 0.051 | F20: 0.051 | G20: 0.051 | H20: 0.051 | I20: 0.051 | J20: 0.051 | K20: 0.051 | L20: 0.051 | M20: 0.051 | N20: 0.051 | O20: Assumption = FY26A.
A21: Other operating liabilities (% of total revenue) | B21: =Model!B44/Model!B8 -> 0.0843865 | C21: =Model!C44/Model!C8 -> 0.081286119 | D21: =Model!D44/Model!D8 -> 0.068890886 | E21: 0.069 | F21: 0.069 | G21: 0.069 | H21: 0.069 | I21: 0.069 | J21: 0.069 | K21: 0.069 | L21: 0.069 | M21: 0.069 | N21: 0.069 | O21: Assumption = FY26A.
A22: Net purchases of financial investments (Rs crore) | C22: =-(Model!C35-Model!B35) -> -109.45 | D22: =-(Model!D35-Model!C35) -> -774.42 | E22: 0 | F22: 0 | G22: 0 | H22: 0 | I22: 0 | J22: 0 | K22: 0 | L22: 0 | M22: 0 | N22: 0 | O22: Assumption: treasury portfolio held flat; surplus cash accumulates in cash.
A23: Net borrowings drawn / (repaid) (Rs crore) | C23: =Model!C45-Model!B45 -> -818.45 | D23: =Model!D45-Model!C45 -> 133.77 | E23: 0 | F23: 0 | G23: 0 | H23: 0 | I23: 0 | J23: 0 | K23: 0 | L23: 0 | M23: 0 | N23: 0 | O23: Assumption: debt held flat.
A24: Dividends paid (% of prior-year net profit) | C24: =-Historical!C111/Historical!B25 -> 0.82819016 | D24: =-Historical!D111/Historical!C25 -> 0.82831311 | E24: 0.85 | F24: 0.85 | G24: 0.85 | H24: 0.85 | I24: 0.85 | J24: 0.85 | K24: 0.85 | L24: 0.85 | M24: 0.85 | N24: 0.85 | O24: Assumption. FY26A paid 82.8% of FY25 profit; Board recommended Rs 90.50/share final dividend for FY26 (c.86% of FY26 profit).
A26: SCENARIO SWITCH (applies to every forecast year)
A27: Active scenario (1 = Bear, 2 = Base, 3 = Bull) | B27: 2 | C27: =CHOOSE(B27,"Bear","Base","Bull") -> Base | D27: Change B to 1, 2 or 3; every sheet updates.
A28: Scenario table | B28: Bear | C28: Base | D28: Bull
A29: Sale of goods growth adjustment (added to base, each year) | B29: -0.02 | C29: 0 | D29: 0.015 | E29: Assumption. Bear: slower volume/pricing. Bull: closer to broker FY27E-28E growth (c.11%).
A30: COGS (% of sale of goods) adjustment (added to base, each year) | B30: 0.006 | C30: 0 | D30: -0.004 | E30: Assumption. Bear: input-cost pressure. Bull: mix / operating leverage.
A31: Live growth adjustment | B31: =CHOOSE($B$27,B29,C29,D29) -> 0
A32: Live COGS adjustment | B32: =CHOOSE($B$27,B30,C30,D30) -> 0
A34: VALUATION AND MARKET INPUTS
A35: Valuation date | B35: 46314 | C35: Date of this analysis.
A36: First forecast year-end (FY27E) | B36: 46477 | C36: Fiscal year ends 31 March.
A37: Current share price (Rs) | B37: 4764 | C37: NSE close on 16-Oct-2026 per Screener.in. UPDATE before presenting.
A38: Face value per share (Rs) | B38: 1 | C38: Per filing.
A39: Shares outstanding (crore) | B39: =Historical!D57/B38 -> 24.09 | C39: Equity share capital Rs 24.09 cr / face value Re 1 = 24.09 crore shares.
A40: Risk-free rate (India 10-year G-Sec yield) | B40: 0.071 | C40: c.7.1% in late Sep 2026 (Trading Economics). UPDATE.
A41: Equity beta | B41: 0.6 | C41: ASSUMPTION. Indian staples betas are low (HUL c.0.6, Nestle India c.0.4 on Equentis). Verify on Bloomberg / NSE.
A42: Equity risk premium | B42: 0.055 | C42: ASSUMPTION. Typical range used for India: 5.0%-6.5%.
A43: Pre-tax cost of debt | B43: 0.08 | C43: ASSUMPTION. Britannia is AAA-rated by CRISIL; borrowings are mostly short-term.
A44: Terminal growth rate | B44: 0.055 | C44: ASSUMPTION. Below long-run nominal GDP growth; staples DCFs typically use 5%-6%.
A45: Mid-year discounting (1 = on, 0 = off) | B45: 1 | C45: Cash flows assumed to arrive evenly through the year.
A46: Britannia TTM EPS to Jun-2026 (Rs) | B46: 108.11 | C46: Screener.in (TTM to June 2026).
A47: 52-week low (Rs) | B47: 4734 | C47: Screener.in as of 16-Oct-2026.
A48: 52-week high (Rs) | B48: 6271 | C48: Screener.in as of 16-Oct-2026.

Sheet Historical
A1: Britannia Industries Ltd (NSE: BRITANNIA) - Historical financials (as reported)
A2: Consolidated, Rs crore, year ended 31 March. Blue = hard-coded from filings; black = formula.
A4: ₹ Crore | B4: FY24A | C4: FY25A | D4: FY26A | E4: Source / note
A5: INCOME STATEMENT
A6: Sale of goods | B6: 16546.21 | C6: 17535.02 | D6: 18858.21 | E6: Britannia audited consolidated results 31-Mar-2026 (filed 7-May-2026) - FY26 and FY25 comparatives; FY24 from Britannia audited consolidated results 31-Mar-2025 (filed 8-May-2025) - FY24 comparatives
A7: Other operating revenues | B7: 223.06 | C7: 407.65 | D7: 293.38
A8: Total revenue from operations | B8: =B6+B7 -> 16769.27 | C8: =C6+C7 -> 17942.67 | D8: =D6+D7 -> 19151.59
A9: Other income | B9: 214.18 | C9: 227.09 | D9: 224.03
A10: Cost of materials consumed | B10: 8546.89 | C10: 9859.45 | D10: 10350.02
A11: Purchases of stock-in-trade | B11: 941.48 | C11: 809.35 | D11: 805.23
A12: Changes in inventories of FG, stock-in-trade and WIP | B12: 3.66 | C12: -64.75 | D12: -22.37
A13: Employee benefits expense | B13: 708.7 | C13: 704.59 | D13: 823.8 | E13: FY26 includes Rs 48.56 cr one-off past service cost on New Labour Codes (per filing note)
A14: Finance costs | B14: 164 | C14: 138.8 | D14: 112.76
A15: Depreciation and amortisation | B15: 300.46 | C15: 313.34 | D15: 336.83
A16: Other expenses | B16: 3398.7 | C16: 3446.88 | D16: 3650.48
A17: Total expenses | B17: =SUM(B10:B16) -> 14063.89 | C17: =SUM(C10:C16) -> 15207.66 | D17: =SUM(D10:D16) -> 16056.75
A18: Profit before share of associates / JV | B18: =B8+B9-B17 -> 2919.56 | C18: =C8+C9-C17 -> 2962.1 | D18: =D8+D9-D17 -> 3318.87
A19: Share of profit / (loss) of associates and JV | B19: -3.19 | C19: -10.74 | D19: -30.09
A20: Exceptional item - expense | B20: 2.9 | C20: 24.79 | D20: 0 | E20: FY25: Voluntary Retirement Scheme cost at one factory (per filing note)
A21: Profit before tax | B21: =B18+B19-B20 -> 2913.47 | C21: =C18+C19-C20 -> 2926.57 | D21: =D18+D19-D20 -> 3288.78
A22: Current tax | B22: 765.69 | C22: 741.68 | D22: 758.37 | E22: FY26 includes net reversal of provisions of Rs 95.39 cr (favourable tax orders)
A23: Deferred tax charge / (credit) | B23: 13.56 | C23: 7.03 | D23: -6.6
A24: Total tax expense | B24: =B22+B23 -> 779.25 | C24: =C22+C23 -> 748.71 | D24: =D22+D23 -> 751.77
A25: Net profit for the year | B25: =B21-B24 -> 2134.22 | C25: =C21-C24 -> 2177.86 | D25: =D21-D24 -> 2537.01
A26: of which: non-controlling interests | B26: -5.59 | C26: -0.87 | D26: 3.52
A27: of which: owners of the company | B27: =B25-B26 -> 2139.81 | C27: =C25-C26 -> 2178.73 | D27: =D25-D26 -> 2533.49
A28: Basic EPS as reported (Rs) | B28: 88.84 | C28: 90.45 | D28: 105.18
A30: BALANCE SHEET - ASSETS
A31: Property, plant and equipment | B31: 2602.94 | C31: 2734.61 | D31: 2672.98 | E31: Britannia audited consolidated results 31-Mar-2026 (filed 7-May-2026) - FY26 and FY25 comparatives. Column order in the PDF text was scrambled; every line reconciled to reported sub-totals (see tie-out).
A32: Capital work-in-progress | B32: 187.54 | C32: 89.2 | D32: 39.04
A33: Investment property | B33: 27.48 | C33: 28.9 | D33: 27.9
A34: Goodwill | B34: 129.82 | C34: 132.78 | D34: 143.95
A35: Other intangible assets | B35: 10.9 | C35: 7.51 | D35: 5.09
A36: Investment in associates and JV | B36: 494.36 | C36: 483.62 | D36: 453.53
A37: Non-current investments | B37: 575.85 | C37: 1270.17 | D37: 1517.71
A38: Non-current loans | B38: 0 | C38: 25 | D38: 25
A39: Other non-current financial assets | B39: 25.5 | C39: 28.19 | D39: 30.99
A40: Deferred tax assets (net) | B40: 43.88 | C40: 36.59 | D40: 43.01
A41: Tax assets (net) | B41: 67.95 | C41: 46.26 | D41: 69.31
A42: Other non-current assets | B42: 58.68 | C42: 42.04 | D42: 25.77
A43: Total non-current assets | B43: =SUM(B31:B42) -> 4224.9 | C43: =SUM(C31:C42) -> 4924.87 | D43: =SUM(D31:D42) -> 5054.28
A44: Inventories | B44: 1181.22 | C44: 1236.51 | D44: 1345.93
A45: Current investments | B45: 1696.51 | C45: 1111.64 | D45: 1638.52
A46: Trade receivables | B46: 393.33 | C46: 448.61 | D46: 469.21
A47: Cash and cash equivalents | B47: 322.8 | C47: 132.78 | D47: 220
A48: Other bank balances | B48: 123.55 | C48: 179.7 | D48: 132.44
A49: Current loans | B49: 460 | C49: 50 | D49: 65
A50: Other current financial assets | B50: 531.13 | C50: 630.46 | D50: 664.53
A51: Other current assets | B51: 133.71 | C51: 123.98 | D51: 142.03
A52: Assets held for sale | B52: 6.41 | C52: 0 | D52: 0
A53: Total current assets | B53: =SUM(B44:B52) -> 4848.66 | C53: =SUM(C44:C52) -> 3913.68 | D53: =SUM(D44:D52) -> 4677.66
A54: TOTAL ASSETS | B54: =B43+B53 -> 9073.56 | C54: =C43+C53 -> 8838.55 | D54: =D43+D53 -> 9731.94
A56: BALANCE SHEET - EQUITY AND LIABILITIES
A57: Equity share capital (face value Re 1) | B57: 24.09 | C57: 24.09 | D57: 24.09
A58: Other equity | B58: 3917.43 | C58: 4331.63 | D58: 5082.47
A59: Non-controlling interests | B59: 24.5 | C59: 25.6 | D59: 29.32
A60: Total equity | B60: =B57+B58+B59 -> 3966.02 | C60: =C57+C58+C59 -> 4381.32 | D60: =D57+D58+D59 -> 5135.88
A61: Non-current borrowings | B61: 904.72 | C61: 712.94 | D61: 286.11
A62: Non-current lease liabilities | B62: 20.13 | C62: 19.45 | D62: 19.31
A63: Other non-current financial liabilities | B63: 65.66 | C63: 72.21 | D63: 72.95
A64: Deferred tax liabilities (net) | B64: 2.06 | C64: 1.8 | D64: 1.62
A65: Non-current provisions | B65: 30.56 | C65: 32.57 | D65: 36.08
A66: Total non-current liabilities | B66: =SUM(B61:B65) -> 1023.13 | C66: =SUM(C61:C65) -> 838.97 | D66: =SUM(D61:D65) -> 416.07
A67: Current borrowings | B67: 1136.49 | C67: 511.83 | D67: 1071.72
A68: Current lease liabilities | B68: 3.62 | C68: 2.29 | D68: 3.14
A69: Trade payables - MSME | B69: 30.83 | C69: 27.83 | D69: 21.41
A70: Trade payables - others | B70: 1596.65 | C70: 1724.4 | D70: 1875
A71: Other current financial liabilities | B71: 497.4 | C71: 429.34 | D71: 442.81
A72: Other current liabilities | B72: 167.29 | C72: 194.7 | D72: 88.67
A73: Current provisions | B73: 559.2 | C73: 604.66 | D73: 594.52
A74: Current tax liabilities (net) | B74: 92.93 | C74: 123.21 | D74: 82.72
A75: Total current liabilities | B75: =SUM(B67:B74) -> 4084.41 | C75: =SUM(C67:C74) -> 3618.26 | D75: =SUM(D67:D74) -> 4179.99
A76: TOTAL EQUITY AND LIABILITIES | B76: =B60+B66+B75 -> 9073.56 | C76: =C60+C66+C75 -> 8838.55 | D76: =D60+D66+D75 -> 9731.94
A78: CASH FLOW STATEMENT
A79: Profit before tax and share of associates (after exceptionals) | B79: 2916.66 | C79: 2937.31 | D79: 3318.87 | E79: FY25 and FY26 per FY26 filing (FY25 comparatives regrouped); FY24 as originally reported in FY25 filing
A80: Depreciation and amortisation | B80: 300.46 | C80: 313.34 | D80: 336.83
A81: Net gain on financial assets at FVTPL | B81: -25.17 | C81: -81.35 | D81: -49.83
A82: Profit on sale of PPE | B82: -0.45 | C82: -1.24 | D82: -1.04
A83: Interest income | B83: -178.75 | C83: -132.8 | D83: -163.01
A84: Finance costs | B84: 164 | C84: 138.8 | D84: 112.76
A85: Operating profit before working capital changes | B85: =SUM(B79:B84) -> 3176.75 | C85: =SUM(C79:C84) -> 3174.06 | D85: =SUM(D79:D84) -> 3554.58
A86: Change in inventories | B86: 12.6 | C86: -54.33 | D86: -105.05
A87: Change in trade receivables | B87: -63.65 | C87: -53.44 | D87: -12.95
A88: Change in other financial and other assets | B88: -24.52 | C88: -88.65 | D88: -28.05
A89: Change in payables, other liabilities and provisions | B89: 236.67 | C89: 202.19 | D89: 24.81
A90: Cash generated from operations | B90: =SUM(B85:B89) -> 3337.85 | C90: =SUM(C85:C89) -> 3179.83 | D90: =SUM(D85:D89) -> 3433.34
A91: Income tax paid (net of refunds) | B91: -764.87 | C91: -689.21 | D91: -821.74
A92: Net cash from operating activities | B92: =B90+B91 -> 2572.98 | C92: =C90+C91 -> 2490.62 | D92: =D90+D91 -> 2611.6
A93: Acquisition of PPE, CWIP and intangibles (capex) | B93: -552.87 | C93: -374.85 | D93: -205.57
A94: Proceeds from sale of PPE | B94: 64.52 | C94: 4.58 | D94: 2.12
A95: Purchase of non-current investments | B95: -190.9 | C95: -945.05 | D95: -613.24
A96: Sale / redemption of non-current investments | B96: 294.22 | C96: 572.16 | D96: 254.35
A97: Purchase / sale of current investments (net) | B97: 476.87 | C97: 347.31 | D97: -362.35
A98: Inter-corporate deposits placed | B98: -610 | C98: -75 | D98: -115
A99: Inter-corporate deposits redeemed | B99: 860 | C99: 460 | D99: 100
A100: Change in other bank balances and deposits | B100: -27.95 | C100: -74.08 | D100: 39.15
A101: Interest received | B101: 170.26 | C101: 151.36 | D101: 143.27
A102: Net cash from investing activities | B102: =SUM(B93:B101) -> 484.15 | C102: =SUM(C93:C101) -> 66.43 | D102: =SUM(D93:D101) -> -757.27
A103: Interest paid | B103: -164.28 | C103: -170.62 | D103: -107.18
A104: Principal payment of lease liabilities | B104: -1.95 | C104: -3.58 | D104: -2.77
...

Sheet Model
A1: Britannia Industries - Integrated three-statement model
A2: Consolidated, Rs crore, FYE 31 March. Historical = links to Historical sheet (green). Forecast = formulas driven by Assumptions (black).
A4: ₹ Crore | B4: FY24A | C4: FY25A | D4: FY26A | E4: FY27E | F4: FY28E | G4: FY29E | H4: FY30E | I4: FY31E | J4: FY32E | K4: FY33E | L4: FY34E | M4: FY35E | N4: FY36E | O4: Notes
A5: INCOME STATEMENT
A6: Sale of goods | B6: =Historical!B6 -> 16546.21 | C6: =Historical!C6 -> 17535.02 | D6: =Historical!D6 -> 18858.21 | E6: =D6*(1+Assumptions!E5+Assumptions!$B$31) -> 20555.449 | F6: =E6*(1+Assumptions!F5+Assumptions!$B$31) -> 22405.439 | G6: =F6*(1+Assumptions!G5+Assumptions!$B$31) -> 24309.902 | H6: =G6*(1+Assumptions!H5+Assumptions!$B$31) -> 26254.694 | I6: =H6*(1+Assumptions!I5+Assumptions!$B$31) -> 28355.069 | J6: =I6*(1+Assumptions!J5+Assumptions!$B$31) -> 30481.699 | K6: =J6*(1+Assumptions!K5+Assumptions!$B$31) -> 32615.418 | L6: =K6*(1+Assumptions!L5+Assumptions!$B$31) -> 34735.421 | ... N6: =M6*(1+Assumptions!N5+Assumptions!$B$31) -> 38844.621
A7: Other operating revenues | B7: =Historical!B7 -> 223.06 | C7: =Historical!C7 -> 407.65 | D7: =Historical!D7 -> 293.38 | E7: =E6*Assumptions!E6 -> 328.88718 | F7: =F6*Assumptions!F6 -> 358.48703 | G7: =G6*Assumptions!G6 -> 388.95843 | H7: =H6*Assumptions!H6 -> 420.0751 | I7: =I6*Assumptions!I6 -> 453.68111 | J7: =J6*Assumptions!J6 -> 487.70719 | K7: =K6*Assumptions!K6 -> 521.84669 | L7: =L6*Assumptions!L6 -> 555.76673 | ... N7: =N6*Assumptions!N6 -> 621.51393
A8: Total revenue from operations | B8: =B6+B7 -> 16769.27 | C8: =C6+C7 -> 17942.67 | D8: =D6+D7 -> 19151.59 | E8: =E6+E7 -> 20884.336 | F8: =F6+F7 -> 22763.926 | G8: =G6+G7 -> 24698.86 | H8: =H6+H7 -> 26674.769 | I8: =I6+I7 -> 28808.75 | ... N8: =N6+N7 -> 39466.135
A9: Cost of goods sold (materials + purchases + inventory change) | B9: =Historical!B10+Historical!B11+Historical!B12 -> 9492.03 | C9: =Historical!C10+Historical!C11+Historical!C12 -> 10604.05 | D9: =Historical!D10+Historical!D11+Historical!D12 -> 11132.88 | E9: =E6*(Assumptions!E7+Assumptions!$B$32) -> 12086.604 | F9: =F6*(Assumptions!F7+Assumptions!$B$32) -> 13129.587 | G9: =G6*(Assumptions!G7+Assumptions!$B$32) -> 14221.292 | H9: =H6*(Assumptions!H7+Assumptions!$B$32) -> 15358.996 | I9: =I6*(Assumptions!I7+Assumptions!$B$32) -> 16587.716 | J9: =J6*(Assumptions!J7+Assumptions!$B$32) -> 17831.794 | K9: =K6*(Assumptions!K7+Assumptions!$B$32) -> 19080.02 | L9: =L6*(Assumptions!L7+Assumptions!$B$32) -> 20320.221 | ... N9: =N6*(Assumptions!N7+Assumptions!$B$32) -> 22724.103 | O9: EBITDA here = revenue - COGS - employee - other expenses (excludes other income); FY26A Rs 3,544 cr ties to broker-reported EBITDA.
A10: Gross profit | B10: =B8-B9 -> 7277.24 | C10: =C8-C9 -> 7338.62 | D10: =D8-D9 -> 8018.71 | E10: =E8-E9 -> 8797.7321 | F10: =F8-F9 -> 9634.3389 | G10: =G8-G9 -> 10477.568 | H10: =H8-H9 -> 11315.773 | I10: =I8-I9 -> 12221.035 | ... N10: =N8-N9 -> 16742.032
A11: Gross margin (% of revenue) | B11: =B10/B8 -> 0.43396284 | C11: =C10/C8 -> 0.40900379 | D11: =D10/D8 -> 0.41869683 | E11: =E10/E8 -> 0.42125984 | F11: =F10/F8 -> 0.42322835 | G11: =G10/G8 -> 0.4242126 | H11: =H10/H8 -> 0.4242126 | I11: =I10/I8 -> 0.4242126 | ... N11: =N10/N8 -> 0.4242126
A12: Employee benefits expense | B12: =Historical!B13 -> 708.7 | C12: =Historical!C13 -> 704.59 | D12: =Historical!D13 -> 823.8 | E12: =E8*Assumptions!E8 -> 877.14212 | F12: =F8*Assumptions!F8 -> 956.08491 | G12: =G8*Assumptions!G8 -> 1037.3521 | H12: =H8*Assumptions!H8 -> 1120.3403 | I12: =I8*Assumptions!I8 -> 1209.9675 | J12: =J8*Assumptions!J8 -> 1300.7151 | K12: =K8*Assumptions!K8 -> 1391.7651 | L12: =L8*Assumptions!L8 -> 1482.2299 | ... N12: =N8*Assumptions!N8 -> 1657.5777
A13: Other expenses | B13: =Historical!B16 -> 3398.7 | C13: =Historical!C16 -> 3446.88 | D13: =Historical!D16 -> 3650.48 | E13: =E8*Assumptions!E9 -> 3968.0239 | F13: =F8*Assumptions!F9 -> 4325.146 | G13: =G8*Assumptions!G9 -> 4692.7834 | H13: =H8*Assumptions!H9 -> 5068.2061 | I13: =I8*Assumptions!I9 -> 5473.6626 | J13: =J8*Assumptions!J9 -> 5884.1873 | K13: =K8*Assumptions!K9 -> 6296.0804 | L13: =L8*Assumptions!L9 -> 6705.3256 | ... N13: =N8*Assumptions!N9 -> 7498.5656
A14: EBITDA | B14: =B10-B12-B13 -> 3169.84 | C14: =C10-C12-C13 -> 3187.15 | D14: =D10-D12-D13 -> 3544.43 | E14: =E10-E12-E13 -> 3952.5662 | F14: =F10-F12-F13 -> 4353.108 | G14: =G10-G12-G13 -> 4747.4321 | H14: =H10-H12-H13 -> 5127.2266 | I14: =I10-I12-I13 -> 5537.4048 | ... N14: =N10-N12-N13 -> 7585.8883
A15: EBITDA margin (% of revenue) | B15: =B14/B8 -> 0.18902671 | C15: =C14/C8 -> 0.17762964 | D15: =D14/D8 -> 0.18507236 | E15: =E14/E8 -> 0.18925984 | F15: =F14/F8 -> 0.19122835 | G15: =G14/G8 -> 0.1922126 | H15: =H14/H8 -> 0.1922126 | I15: =I14/I8 -> 0.1922126 | ... N15: =N14/N8 -> 0.1922126
A16: Depreciation and amortisation | B16: =Historical!B15 -> 300.46 | C16: =Historical!C15 -> 313.34 | D16: =Historical!D15 -> 336.83 | E16: =D33*Assumptions!E10 -> 317.7856 | F16: =E33*Assumptions!F10 -> 328.77472 | G16: =F33*Assumptions!G10 -> 342.69014 | H16: =G33*Assumptions!H10 -> 359.33172 | I16: =H33*Assumptions!I10 -> 378.48972 | J16: =I33*Assumptions!J10 -> 400.2351 | K16: =J33*Assumptions!K10 -> 424.34194 | L16: =K33*Assumptions!L10 -> 450.56631 | ... N16: =M33*Assumptions!N10 -> 508.29276
A17: EBIT | B17: =B14-B16 -> 2869.38 | C17: =C14-C16 -> 2873.81 | D17: =D14-D16 -> 3207.6 | E17: =E14-E16 -> 3634.7806 | F17: =F14-F16 -> 4024.3333 | G17: =G14-G16 -> 4404.7419 | H17: =H14-H16 -> 4767.8949 | I17: =I14-I16 -> 5158.915 | ... N17: =N14-N16 -> 7077.5956
A18: Other income | B18: =Historical!B9 -> 214.18 | C18: =Historical!C9 -> 227.09 | D18: =Historical!D9 -> 224.03 | E18: =(D35+D36+D37)*Assumptions!E12 -> 251.9069 | F18: =(E35+E36+E37)*Assumptions!F12 -> 293.64991 | G18: =(F35+F36+F37)*Assumptions!G12 -> 340.77714 | H18: =(G35+G36+G37)*Assumptions!H12 -> 389.4514 | I18: =(H35+H36+H37)*Assumptions!I12 -> 439.13205 | J18: =(I35+I36+I37)*Assumptions!J12 -> 492.15031 | K18: =(J35+J36+J37)*Assumptions!K12 -> 547.47496 | L18: =(K35+K36+K37)*Assumptions!L12 -> 605.03995 | ... N18: =(M35+M36+M37)*Assumptions!N12 -> 726.63087
A19: Finance costs | B19: =Historical!B14 -> 164 | C19: =Historical!C14 -> 138.8 | D19: =Historical!D14 -> 112.76 | E19: =D45*Assumptions!E13 -> 110.4224 | F19: =E45*Assumptions!F13 -> 110.4224 | G19: =F45*Assumptions!G13 -> 110.4224 | H19: =G45*Assumptions!H13 -> 110.4224 | I19: =H45*Assumptions!I13 -> 110.4224 | J19: =I45*Assumptions!J13 -> 110.4224 | K19: =J45*Assumptions!K13 -> 110.4224 | L19: =K45*Assumptions!L13 -> 110.4224 | ... N19: =M45*Assumptions!N13 -> 110.4224
A20: Share of profit / (loss) of associates and JV | B20: =Historical!B19 -> -3.19 | C20: =Historical!C19 -> -10.74 | D20: =Historical!D19 -> -30.09 | E20: =Assumptions!E14 -> -15 | F20: =Assumptions!F14 -> -15 | G20: =Assumptions!G14 -> -15 | H20: =Assumptions!H14 -> -15 | I20: =Assumptions!I14 -> -15 | J20: =Assumptions!J14 -> -15 | K20: =Assumptions!K14 -> -15 | L20: =Assumptions!L14 -> -15 | ... N20: =Assumptions!N14 -> -15
A21: Exceptional items (expense) | B21: =Historical!B20 -> 2.9 | C21: =Historical!C20 -> 24.79 | D21: =Historical!D20 -> 0 | E21: =0 -> 0 | F21: =0 -> 0 | G21: =0 -> 0 | H21: =0 -> 0 | I21: =0 -> 0 | J21: =0 -> 0 | K21: =0 -> 0 | L21: =0 -> 0 | ... N21: =0 -> 0
A22: Profit before tax | B22: =B17+B18-B19+B20-B21 -> 2913.47 | C22: =C17+C18-C19+C20-C21 -> 2926.57 | D22: =D17+D18-D19+D20-D21 -> 3288.78 | E22: =E17+E18-E19+E20-E21 -> 3761.2651 | F22: =F17+F18-F19+F20-F21 -> 4192.5608 | G22: =G17+G18-G19+G20-G21 -> 4620.0967 | H22: =H17+H18-H19+H20-H21 -> 5031.9239 | I22: =I17+I18-I19+I20-I21 -> 5472.6247 | ... N22: =N17+N18-N19+N20-N21 -> 7678.804
A23: Tax expense | B23: =Historical!B24 -> 779.25 | C23: =Historical!C24 -> 748.71 | D23: =Historical!D24 -> 751.77 | E23: =E22*Assumptions!E15 -> 947.83879 | F23: =F22*Assumptions!F15 -> 1056.5253 | G23: =G22*Assumptions!G15 -> 1164.2644 | H23: =H22*Assumptions!H15 -> 1268.0448 | I23: =I22*Assumptions!I15 -> 1379.1014 | J23: =J22*Assumptions!J15 -> 1491.6391 | K23: =K22*Assumptions!K15 -> 1604.5118 | L23: =L22*Assumptions!L15 -> 1716.7404 | ... N23: =N22*Assumptions!N15 -> 1935.0586
A24: Net profit | B24: =B22-B23 -> 2134.22 | C24: =C22-C23 -> 2177.86 | D24: =D22-D23 -> 2537.01 | E24: =E22-E23 -> 2813.4263 | F24: =F22-F23 -> 3136.0355 | G24: =G22-G23 -> 3455.8323 | H24: =H22-H23 -> 3763.8791 | I24: =I22-I23 -> 4093.5233 | ... N24: =N22-N23 -> 5743.7454
A25: of which non-controlling interests | B25: =Historical!B26 -> -5.59 | C25: =Historical!C26 -> -0.87 | D25: =Historical!D26 -> 3.52 | E25: =Assumptions!E16 -> 0 | F25: =Assumptions!F16 -> 0 | G25: =Assumptions!G16 -> 0 | H25: =Assumptions!H16 -> 0 | I25: =Assumptions!I16 -> 0 | J25: =Assumptions!J16 -> 0 | K25: =Assumptions!K16 -> 0 | L25: =Assumptions!L16 -> 0 | ... N25: =Assumptions!N16 -> 0
A26: Net profit to owners | B26: =B24-B25 -> 2139.81 | C26: =C24-C25 -> 2178.73 | D26: =D24-D25 -> 2533.49 | E26: =E24-E25 -> 2813.4263 | F26: =F24-F25 -> 3136.0355 | G26: =G24-G25 -> 3455.8323 | H26: =H24-H25 -> 3763.8791 | I26: =I24-I25 -> 4093.5233 | ... N26: =N24-N25 -> 5743.7454
A27: EPS (Rs) | B27: =Historical!B28 -> 88.84 | C27: =Historical!C28 -> 90.45 | D27: =Historical!D28 -> 105.18 | E27: =E26/Assumptions!$B$39 -> 116.78814 | F27: =F26/Assumptions!$B$39 -> 130.17997 | G27: =G26/Assumptions!$B$39 -> 143.45506 | H27: =H26/Assumptions!$B$39 -> 156.24239 | I27: =I26/Assumptions!$B$39 -> 169.92625 | J27: =J26/Assumptions!$B$39 -> 183.7926 | K27: =K26/Assumptions!$B$39 -> 197.70023 | L27: =L26/Assumptions!$B$39 -> 211.5285 | ... N27: =N26/Assumptions!$B$39 -> 238.42862 | O27: Historical EPS as reported; forecast EPS = net profit to owners / 24.09 crore shares.
A28: Revenue growth | C28: =C8/B8-1 -> 0.069973231 | D28: =D8/C8-1 -> 0.067376817 | E28: =E8/D8-1 -> 0.090475312 | F28: =F8/E8-1 -> 0.09 | G28: =G8/F8-1 -> 0.085 | H28: =H8/G8-1 -> 0.08 | I28: =I8/H8-1 -> 0.08 | J28: =J8/I8-1 -> 0.075 | ... N28: =N8/M8-1 -> 0.055
A29: Net profit growth | C29: =C24/B24-1 -> 0.020447751 | D29: =D24/C24-1 -> 0.16490959 | E29: =E24/D24-1 -> 0.10895356 | F29: =F24/E24-1 -> 0.11466773 | G29: =G24/F24-1 -> 0.10197488 | H29: =H24/G24-1 -> 0.089138233 | I29: =I24/H24-1 -> 0.087580971 | J29: =J24/I24-1 -> 0.081602203 | ... N29: =N24/M24-1 -> 0.058979354
A30: Effective tax rate | B30: =B23/B22 -> 0.26746457 | C30: =C23/C22 -> 0.25583191 | D30: =D23/D22 -> 0.22858628 | E30: =E23/E22 -> 0.252 | F30: =F23/F22 -> 0.252 | G30: =G23/G22 -> 0.252 | H30: =H23/H22 -> 0.252 | I30: =I23/I22 -> 0.252 | ... N30: =N23/N22 -> 0.252
A32: BALANCE SHEET (condensed)
A33: Net fixed assets and intangibles (PPE, CWIP, inv. property, goodwill, intangibles) | B33: =Historical!B31+Historical!B32+Historical!B33+Historical!B34+Historical!B35 -> 2958.68 | C33: =Historical!C31+Historical!C32+Historical!C33+Historical!C34+Historical!C35 -> 2993 | D33: =Historical!D31+Historical!D32+Historical!D33+Historical!D34+Historical!D35 -> 2888.96 | E33: =D33-E63-E16 -> 2988.8611 | F33: =E33-F63-F16 -> 3115.3649 | G33: =F33-G63-G16 -> 3266.652 | H33: =G33-H63-H16 -> 3440.8156 | I33: =H33-I63-I16 -> 3638.5009 | J33: =I33-J63-J16 -> 3857.654 | K33: =J33-K63-K16 -> 4096.0573 | L33: =K33-L63-L16 -> 4351.3148 | ... N33: =M33-N63-N16 -> 4901.8732
A34: Investment in associates and JV | B34: =Historical!B36 -> 494.36 | C34: =Historical!C36 -> 483.62 | D34: =Historical!D36 -> 453.53 | E34: =D34+E20 -> 438.53 | F34: =E34+F20 -> 423.53 | G34: =F34+G20 -> 408.53 | H34: =G34+H20 -> 393.53 | I34: =H34+I20 -> 378.53 | J34: =I34+J20 -> 363.53 | K34: =J34+K20 -> 348.53 | L34: =K34+L20 -> 333.53 | ... N34: =M34+N20 -> 303.53
A35: Financial investments (non-current + current) | B35: =Historical!B37+Historical!B45 -> 2272.36 | C35: =Historical!C37+Historical!C45 -> 2381.81 | D35: =Historical!D37+Historical!D45 -> 3156.23 | E35: =D35-E64 -> 3156.23 | F35: =E35-F64 -> 3156.23 | G35: =F35-G64 -> 3156.23 | H35: =G35-H64 -> 3156.23 | I35: =H35-I64 -> 3156.23 | J35: =I35-J64 -> 3156.23 | K35: =J35-K64 -> 3156.23 | L35: =K35-L64 -> 3156.23 | ... N35: =M35-N64 -> 3156.23
A36: Cash and cash equivalents | B36: =Historical!B47 -> 322.8 | C36: =Historical!C47 -> 132.78 | D36: =Historical!D47 -> 220 | E36: =E71 -> 816.32879 | F36: =F71 -> 1489.5748 | G36: =G71 -> 2184.9214 | H36: =H71 -> 2894.645 | I36: =I71 -> 3652.0487 | J36: =J71 -> 4442.4008 | K36: =K71 -> 5264.7578 | L36: =L71 -> 6118.3046 | ... N36: =N71 -> 7913.4324
A37: Other treasury assets (bank balances + loans) | B37: =Historical!B48+Historical!B38+Historical!B49 -> 583.55 | C37: =Historical!C48+Historical!C38+Historical!C49 -> 254.7 | D37: =Historical!D48+Historical!D38+Historical!D49 -> 222.44 | E37: =D37 -> 222.44 | F37: =E37 -> 222.44 | G37: =F37 -> 222.44 | H37: =G37 -> 222.44 | I37: =H37 -> 222.44 | J37: =I37 -> 222.44 | K37: =J37 -> 222.44 | L37: =K37 -> 222.44 | ... N37: =M37 -> 222.44
A38: Inventories | B38: =Historical!B44 -> 1181.22 | C38: =Historical!C44 -> 1236.51 | D38: =Historical!D44 -> 1345.93 | E38: =Assumptions!E17*E9/365 -> 1457.0153 | F38: =Assumptions!F17*F9/365 -> 1582.7448 | G38: =Assumptions!G17*G9/365 -> 1714.3476 | H38: =Assumptions!H17*H9/365 -> 1851.4954 | I38: =Assumptions!I17*I9/365 -> 1999.615 | J38: =Assumptions!J17*J9/365 -> 2149.5861 | K38: =Assumptions!K17*K9/365 -> 2300.0572 | L38: =Assumptions!L17*L9/365 -> 2449.5609 | ... N38: =Assumptions!N17*N9/365 -> 2739.344
A39: Trade receivables | B39: =Historical!B46 -> 393.33 | C39: =Historical!C46 -> 448.61 | D39: =Historical!D46 -> 469.21 | E39: =Assumptions!E18*E8/365 -> 514.95623 | F39: =Assumptions!F18*F8/365 -> 561.30229 | G39: =Assumptions!G18*G8/365 -> 609.01299 | H39: =Assumptions!H18*H8/365 -> 657.73403 | I39: =Assumptions!I18*I8/365 -> 710.35275 | J39: =Assumptions!J18*J8/365 -> 763.62921 | K39: =Assumptions!K18*K8/365 -> 817.08325 | L39: =Assumptions!L18*L8/365 -> 870.19366 | ... N39: =Assumptions!N18*N8/365 -> 973.13757
A40: Other operating assets | B40: =Historical!B39+Historical!B40+Historical!B41+Historical!B42+Historical!B50+Historical!B51+Historical!B52 -> 867.26 | C40: =Historical!C39+Historical!C40+Historical!C41+Historical!C42+Historical!C50+Historical!C51+Historical!C52 -> 907.52 | D40: =Historical!D39+Historical!D40+Historical!D41+Historical!D42+Historical!D50+Historical!D51+Historical!D52 -> 975.64 | E40: =Assumptions!E20*E8 -> 1065.1011 | F40: =Assumptions!F20*F8 -> 1160.9602 | G40: =Assumptions!G20*G8 -> 1259.6419 | H40: =Assumptions!H20*H8 -> 1360.4132 | I40: =Assumptions!I20*I8 -> 1469.2463 | J40: =Assumptions!J20*J8 -> 1579.4397 | K40: =Assumptions!K20*K8 -> 1690.0005 | L40: =Assumptions!L20*L8 -> 1799.8506 | ... N40: =Assumptions!N20*N8 -> 2012.7729
A41: Total assets | B41: =B33+B34+B35+B36+B37+B38+B39+B40 -> 9073.56 | C41: =C33+C34+C35+C36+C37+C38+C39+C40 -> 8838.55 | D41: =D33+D34+D35+D36+D37+D38+D39+D40 -> 9731.94 | E41: =E33+E34+E35+E36+E37+E38+E39+E40 -> 10659.463 | F41: =F33+F34+F35+F36+F37+F38+F39+F40 -> 11712.147 | G41: =G33+G34+G35+G36+G37+G38+G39+G40 -> 12821.776 | H41: =H33+H34+H35+H36+H37+H38+H39+H40 -> 13977.303 | I41: =I33+I34+I35+I36+I37+I38+I39+I40 -> 15226.964 | ... N41: =N33+N34+N35+N36+N37+N38+N39+N40 -> 22222.76
A43: Trade payables | B43: =Historical!B69+Historical!B70 -> 1627.48 | C43: =Historical!C69+Historical!C70 -> 1752.23 | D43: =Historical!D69+Historical!D70 -> 1896.41 | E43: =Assumptions!E19*(E9+E13)/365 -> 2045.3156 | F43: =Assumptions!F19*(F9+F13)/365 -> 2223.6852 | G43: =Assumptions!G19*(G9+G13)/365 -> 2409.6014 | H43: =Assumptions!H19*(H9+H13)/365 -> 2602.3696 | I43: =Assumptions!I19*(I9+I13)/365 -> 2810.5591 | J43: =Assumptions!J19*(J9+J13)/365 -> 3021.3511 | K43: =Assumptions!K19*(K9+K13)/365 -> 3232.8456 | L43: =Assumptions!L19*(L9+L13)/365 -> 3442.9806 | ... N43: =Assumptions!N19*(N9+N13)/365 -> 3850.2852
A44: Other operating liabilities (provisions, other liabilities, tax) | B44: =Historical!B63+Historical!B64+Historical!B65+Historical!B71+Historical!B72+Historical!B73+Historical!B74 -> 1415.1 | C44: =Historical!C63+Historical!C64+Historical!C65+Historical!C71+Historical!C72+Historical!C73+Historical!C74 -> 1458.49 | D44: =Historical!D63+Historical!D64+Historical!D65+Historical!D71+Historical!D72+Historical!D73+Historical!D74 -> 1319.37 | E44: =Assumptions!E21*E8 -> 1441.0192 | F44: =Assumptions!F21*F8 -> 1570.7109 | G44: =Assumptions!G21*G8 -> 1704.2213 | H44: =Assumptions!H21*H8 -> 1840.5591 | I44: =Assumptions!I21*I8 -> 1987.8038 | J44: =Assumptions!J21*J8 -> 2136.8891 | K44: =Assumptions!K21*K8 -> 2286.4713 | L44: =Assumptions!L21*L8 -> 2435.0919 | ... N44: =Assumptions!N21*N8 -> 2723.1633
A45: Borrowings incl. lease liabilities | B45: =Historical!B61+Historical!B62+Historical!B67+Historical!B68 -> 2064.96 | C45: =Historical!C61+Historical!C62+Historical!C67+Historical!C68 -> 1246.51 | D45: =Historical!D61+Historical!D62+Historical!D67+Historical!D68 -> 1380.28 | E45: =D45+E66 -> 1380.28 | F45: =E45+F66 -> 1380.28 | G45: =F45+G66 -> 1380.28 | H45: =G45+H66 -> 1380.28 | I45: =H45+I66 -> 1380.28 | J45: =I45+J66 -> 1380.28 | K45: =J45+K66 -> 1380.28 | L45: =K45+L66 -> 1380.28 | ... N45: =M45+N66 -> 1380.28
A46: Total equity (incl. NCI) | B46: =Historical!B60 -> 3966.02 | C46: =Historical!C60 -> 4381.32 | D46: =Historical!D60 -> 5135.88 | E46: =D46+E24+E67 -> 5792.8478 | F46: =E46+F24+F67 -> 6537.4709 | G46: =F46+G24+G67 -> 7327.6731 | H46: =G46+H24+H67 -> 8154.0947 | I46: =H46+I24+I67 -> 9048.3207 | J46: =I46+J24+J67 -> 9996.3898 | K46: =J46+K24+K67 -> 10995.559 | L46: =K46+L24+L67 -> 12043.072 | ... N46: =M46+N24+N67 -> 14269.032
A47: Total equity and liabilities | B47: =B43+B44+B45+B46 -> 9073.56 | C47: =C43+C44+C45+C46 -> 8838.55 | D47: =D43+D44+D45+D46 -> 9731.94 | E47: =E43+E44+E45+E46 -> 10659.463 | F47: =F43+F44+F45+F46 -> 11712.147 | G47: =G43+G44+G45+G46 -> 12821.776 | H47: =H43+H44+H45+H46 -> 13977.303 | I47: =I43+I44+I45+I46 -> 15226.964 | ... N47: =N43+N44+N45+N46 -> 22222.76
A48: Balance check (assets - liabilities - equity) | B48: =ROUND(B41-B47,2) -> 0 | C48: =ROUND(C41-C47,2) -> 0 | D48: =ROUND(D41-D47,2) -> 0 | E48: =ROUND(E41-E47,2) -> 0 | F48: =ROUND(F41-F47,2) -> 0 | G48: =ROUND(G41-G47,2) -> 0 | H48: =ROUND(H41-H47,2) -> 0 | I48: =ROUND(I41-I47,2) -> 0 | ... N48: =ROUND(N41-N47,2) -> 0
A50: Net working capital (inv + rec + other op. assets - payables - other op. liabilities) | B50: =B38+B39+B40-B43-B44 -> -600.77 | C50: =C38+C39+C40-C43-C44 -> -618.08 | D50: =D38+D39+D40-D43-D44 -> -425 | E50: =E38+E39+E40-E43-E44 -> -449.26214 | F50: =F38+F39+F40-F43-F44 -> -489.38881 | G50: =G38+G39+G40-G43-G44 -> -530.82036 | H50: =H38+H39+H40-H43-H44 -> -573.28598 | I50: =I38+I39+I40-I43-I44 -> -619.14886 | ... N50: =N38+N39+N40-N43-N44 -> -848.19411
A51: Net cash / (debt): cash + investments + other treasury - borrowings | B51: =B36+B35+B37-B45 -> 1113.75 | C51: =C36+C35+C37-C45 -> 1522.78 | D51: =D36+D35+D37-D45 -> 2218.39 | E51: =E36+E35+E37-E45 -> 2814.7188 | F51: =F36+F35+F37-F45 -> 3487.9648 | G51: =G36+G35+G37-G45 -> 4183.3114 | H51: =H36+H35+H37-H45 -> 4893.035 | I51: =I36+I35+I37-I45 -> 5650.4387 | ... N51: =N36+N35+N37-N45 -> 9911.8224
A53: CASH FLOW STATEMENT (projection basis: interest sits inside net profit)
A54: Net profit | E54: =E24 -> 2813.4263 | F54: =F24 -> 3136.0355 | G54: =G24 -> 3455.8323 | H54: =H24 -> 3763.8791 | I54: =I24 -> 4093.5233 | J54: =J24 -> 4427.5638 | K54: =K24 -> 4762.5986 | L54: =L24 -> 5095.7216 | ... N54: =N24 -> 5743.7454 | O54: Forecast cash flow is a simplified indirect build; reported FY24A-FY26A cash flows (rows above) classify interest in investing/financing.
A55: Add: depreciation and amortisation | E55: =E16 -> 317.7856 | F55: =F16 -> 328.77472 | G55: =G16 -> 342.69014 | H55: =H16 -> 359.33172 | I55: =I16 -> 378.48972 | J55: =J16 -> 400.2351 | K55: =K16 -> 424.34194 | L55: =L16 -> 450.56631 | ... N55: =N16 -> 508.29276
A56: Add back: share of loss of associates (non-cash) | E56: =-E20 -> 15 | F56: =-F20 -> 15 | G56: =-G20 -> 15 | H56: =-H20 -> 15 | I56: =-I20 -> 15 | J56: =-J20 -> 15 | K56: =-K20 -> 15 | L56: =-L20 -> 15 | ... N56: =-N20 -> 15
A57: (Increase) / decrease in inventories | E57: =-(E38-D38) -> -111.08527 | F57: =-(F38-E38) -> -125.72952 | G57: =-(G38-F38) -> -131.6028 | H57: =-(H38-G38) -> -137.14781 | I57: =-(I38-H38) -> -148.11963 | J57: =-(J38-I38) -> -149.97113 | K57: =-(K38-J38) -> -150.47103 | L57: =-(L38-K38) -> -149.50372 | ... N57: =-(N38-M38) -> -142.8094
A58: (Increase) / decrease in receivables | E58: =-(E39-D39) -> -45.746232 | F58: =-(F39-E39) -> -46.346061 | G58: =-(G39-F39) -> -47.710695 | H58: =-(H39-G39) -> -48.721039 | I58: =-(I39-H39) -> -52.618722 | J58: =-(J39-I39) -> -53.276456 | K58: =-(K39-J39) -> -53.454044 | L58: =-(L39-K39) -> -53.110411 | ... N58: =-(N39-M39) -> -50.73229
A59: (Increase) / decrease in other operating assets | E59: =-(E40-D40) -> -89.46114 | F59: =-(F40-E40) -> -95.859103 | G59: =-(G40-F40) -> -98.681621 | H59: =-(H40-G40) -> -100.77135 | I59: =-(I40-H40) -> -108.83306 | J59: =-(J40-I40) -> -110.19347 | K59: =-(K40-J40) -> -110.56078 | L59: =-(L40-K40) -> -109.85003 | ... N59: =-(N40-M40) -> -104.93129
A60: Increase / (decrease) in payables | E60: =E43-D43 -> 148.9056 | F60: =F43-E43 -> 178.36962 | G60: =G43-F43 -> 185.91623 | H60: =H43-G43 -> 192.76812 | I60: =I43-H43 -> 208.18957 | J60: =J43-I43 -> 210.79193 | K60: =K43-J43 -> 211.49457 | L60: =L43-K43 -> 210.13497 | ... N60: =N43-M43 -> 200.72577
A61: Increase / (decrease) in other operating liabilities | E61: =E44-D44 -> 121.64919 | F61: =F44-E44 -> 129.69173 | G61: =G44-F44 -> 133.51043 | H61: =H44-G44 -> 136.33771 | I61: =I44-H44 -> 147.24472 | J61: =J44-I44 -> 149.08528 | K61: =K44-J44 -> 149.58223 | L61: =L44-K44 -> 148.62063 | ... N61: =N44-M44 -> 141.96586
A62: Cash flow from operations | B62: =Historical!B92 -> 2572.98 | C62: =Historical!C92 -> 2490.62 | D62: =Historical!D92 -> 2611.6 | E62: =SUM(E54:E61) -> 3170.474 | F62: =SUM(F54:F61) -> 3519.9369 | G62: =SUM(G54:G61) -> 3854.954 | H62: =SUM(H54:H61) -> 4180.6764 | I62: =SUM(I54:I61) -> 4532.8759 | J62: =SUM(J54:J61) -> 4889.2351 | K62: =SUM(K54:K61) -> 5248.5315 | L62: =SUM(L54:L61) -> 5607.5794 | ... N62: =SUM(N54:N61) -> 6311.2568
A63: Capital expenditure | B63: =Historical!B93 -> -552.87 | C63: =Historical!C93 -> -374.85 | D63: =Historical!D93 -> -205.57 | E63: =-E8*Assumptions!E11 -> -417.68672 | F63: =-F8*Assumptions!F11 -> -455.27853 | G63: =-G8*Assumptions!G11 -> -493.9772 | H63: =-H8*Assumptions!H11 -> -533.49538 | I63: =-I8*Assumptions!I11 -> -576.17501 | J63: =-J8*Assumptions!J11 -> -619.38813 | K63: =-K8*Assumptions!K11 -> -662.7453 | L63: =-L8*Assumptions!L11 -> -705.82375 | ... N63: =-N8*Assumptions!N11 -> -789.3227
A64: Net (purchase) / sale of financial investments | E64: =-Assumptions!E22 -> 0 | F64: =-Assumptions!F22 -> 0 | G64: =-Assumptions!G22 -> 0 | H64: =-Assumptions!H22 -> 0 | I64: =-Assumptions!I22 -> 0 | J64: =-Assumptions!J22 -> 0 | K64: =-Assumptions!K22 -> 0 | L64: =-Assumptions!L22 -> 0 | ... N64: =-Assumptions!N22 -> 0
A65: Cash flow from investing | B65: =Historical!B102 -> 484.15 | C65: =Historical!C102 -> 66.43 | D65: =Historical!D102 -> -757.27 | E65: =E63+E64 -> -417.68672 | F65: =F63+F64 -> -455.27853 | G65: =G63+G64 -> -493.9772 | H65: =H63+H64 -> -533.49538 | I65: =I63+I64 -> -576.17501 | J65: =J63+J64 -> -619.38813 | K65: =K63+K64 -> -662.7453 | L65: =L63+L64 -> -705.82375 | ... N65: =N63+N64 -> -789.3227
A66: Net borrowings drawn / (repaid) | E66: =Assumptions!E23 -> 0 | F66: =Assumptions!F23 -> 0 | G66: =Assumptions!G23 -> 0 | H66: =Assumptions!H23 -> 0 | I66: =Assumptions!I23 -> 0 | J66: =Assumptions!J23 -> 0 | K66: =Assumptions!K23 -> 0 | L66: =Assumptions!L23 -> 0 | ... N66: =Assumptions!N23 -> 0
A67: Dividends paid | B67: =Historical!B111 -> -1732.47 | C67: =Historical!C111 -> -1767.54 | D67: =Historical!D111 -> -1803.95 | E67: =-Assumptions!E24*D24 -> -2156.4585 | F67: =-Assumptions!F24*E24 -> -2391.4123 | G67: =-Assumptions!G24*F24 -> -2665.6301 | H67: =-Assumptions!H24*G24 -> -2937.4575 | I67: =-Assumptions!I24*H24 -> -3199.2972 | J67: =-Assumptions!J24*I24 -> -3479.4948 | K67: =-Assumptions!K24*J24 -> -3763.4292 | L67: =-Assumptions!L24*K24 -> -4048.2088 | ... N67: =-Assumptions!N24*M24 -> -4610.2727 | O67: Forecast dividends paid in year t = payout % x net profit of year t-1 (final dividend is paid after year-end).
A68: Cash flow from financing | B68: =Historical!B112 -> -2839.13 | C68: =Historical!C112 -> -2753.9 | D68: =Historical!D112 -> -1782.62 | E68: =E66+E67 -> -2156.4585 | F68: =F66+F67 -> -2391.4123 | G68: =G66+G67 -> -2665.6301 | H68: =H66+H67 -> -2937.4575 | I68: =I66+I67 -> -3199.2972 | J68: =J66+J67 -> -3479.4948 | K68: =K66+K67 -> -3763.4292 | L68: =L66+L67 -> -4048.2088 | ... N68: =N66+N67 -> -4610.2727
A69: Net change in cash | B69: =Historical!B113 -> 218 | C69: =Historical!C113 -> -196.85 | D69: =Historical!D113 -> 71.71 | E69: =E62+E65+E68 -> 596.32879 | F69: =F62+F65+F68 -> 673.24601 | G69: =G62+G65+G68 -> 695.34664 | H69: =H62+H65+H68 -> 709.7236 | I69: =I62+I65+I68 -> 757.40364 | J69: =J62+J65+J68 -> 790.35214 | K69: =K62+K65+K68 -> 822.35698 | L69: =L62+L65+L68 -> 853.54679 | ... N69: =N62+N65+N68 -> 911.66143
A70: Opening cash | B70: =Historical!B115 -> 100.16 | C70: =Historical!C115 -> 319.45 | D70: =Historical!D115 -> 125.24 | E70: =D36 -> 220 | F70: =E36 -> 816.32879 | G70: =F36 -> 1489.5748 | H70: =G36 -> 2184.9214 | I70: =H36 -> 2894.645 | J70: =I36 -> 3652.0487 | K70: =J36 -> 4442.4008 | L70: =K36 -> 5264.7578 | ... N70: =M36 -> 7001.7709
A71: Closing cash | B71: =Historical!B116 -> 319.45 | C71: =Historical!C116 -> 125.24 | D71: =Historical!D116 -> 212.84 | E71: =E70+E69 -> 816.32879 | F71: =F70+F69 -> 1489.5748 | G71: =G70+G69 -> 2184.9214 | H71: =H70+H69 -> 2894.645 | I71: =I70+I69 -> 3652.0487 | J71: =J70+J69 -> 4442.4008 | K71: =K70+K69 -> 5264.7578 | L71: =L70+L69 -> 6118.3046 | ... N71: =N70+N69 -> 7913.4324 | O71: Reported closing cash is net of bank overdraft (Rs 212.84 cr FY26A) vs balance sheet cash of Rs 220.00 cr; forecast opens from balance sheet cash.

Sheet DCF
A1: Discounted cash flow valuation
A2: Unlevered free cash flow to firm, Rs crore. Valuation as of the date on the Assumptions sheet.
A4: COST OF CAPITAL (WACC)
A5: Active scenario | B5: =Assumptions!C27 -> Base
A6: Risk-free rate | B6: =Assumptions!$B$40 -> 0.071
A7: Equity beta | B7: =Assumptions!$B$41 -> 0.6
A8: Equity risk premium | B8: =Assumptions!$B$42 -> 0.055
A9: Cost of equity (CAPM) = Rf + beta x ERP | B9: =B6+B7*B8 -> 0.104
A10: Pre-tax cost of debt | B10: =Assumptions!$B$43 -> 0.08
A11: Tax rate | B11: =Assumptions!E15 -> 0.252
A12: After-tax cost of debt | B12: =B10*(1-B11) -> 0.05984
A13: Market capitalisation (Rs crore) | B13: =Assumptions!$B$37*Assumptions!$B$39 -> 114764.76 | C13: Current price x shares outstanding
A14: Borrowings incl. leases (Rs crore, 31-Mar-2026) | B14: =Model!D45 -> 1380.28
A15: Weight of equity | B15: =B13/(B13+B14) -> 0.98811589
A16: Weight of debt | B16: =1-B15 -> 0.011884106
A17: WACC | B17: =B15*B9+B16*B12 -> 0.1034752
A18: Terminal growth rate | B18: =Assumptions!$B$44 -> 0.055
A19: Mid-year convention (1 = on) | B19: =Assumptions!$B$45 -> 1
A20: Fraction of FY27E remaining after valuation date | B20: =MAX(0,MIN(1,(Assumptions!B36-Assumptions!B35)/365)) -> 0.44657534 | C20: Only the post-valuation-date part of FY27E cash flow is counted
A22: UNLEVERED FREE CASH FLOW
A23: ₹ Crore | B23: FY24A | C23: FY25A | D23: FY26A | E23: FY27E | F23: FY28E | G23: FY29E | H23: FY30E | I23: FY31E | J23: FY32E | K23: FY33E | L23: FY34E | M23: FY35E | N23: FY36E | O23: Notes
A24: EBITDA | C24: =Model!C14 -> 3187.15 | D24: =Model!D14 -> 3544.43 | E24: =Model!E14 -> 3952.5662 | F24: =Model!F14 -> 4353.108 | G24: =Model!G14 -> 4747.4321 | H24: =Model!H14 -> 5127.2266 | I24: =Model!I14 -> 5537.4048 | J24: =Model!J14 -> 5952.7101 | ... N24: =Model!N14 -> 7585.8883
A25: Less: D&A | C25: =-Model!C16 -> -313.34 | D25: =-Model!D16 -> -336.83 | E25: =-Model!E16 -> -317.7856 | F25: =-Model!F16 -> -328.77472 | G25: =-Model!G16 -> -342.69014 | H25: =-Model!H16 -> -359.33172 | I25: =-Model!I16 -> -378.48972 | J25: =-Model!J16 -> -400.2351 | ... N25: =-Model!N16 -> -508.29276
A26: EBIT | C26: =C24+C25 -> 2873.81 | D26: =D24+D25 -> 3207.6 | E26: =E24+E25 -> 3634.7806 | F26: =F24+F25 -> 4024.3333 | G26: =G24+G25 -> 4404.7419 | H26: =H24+H25 -> 4767.8949 | I26: =I24+I25 -> 5158.915 | J26: =J24+J25 -> 5552.475 | ... N26: =N24+N25 -> 7077.5956
A27: Less: tax on EBIT | C27: =-C26*$B$11 -> -724.20012 | D27: =-D26*$B$11 -> -808.3152 | E27: =-E26*$B$11 -> -915.9647 | F27: =-F26*$B$11 -> -1014.132 | G27: =-G26*$B$11 -> -1109.995 | H27: =-H26*$B$11 -> -1201.5095 | I27: =-I26*$B$11 -> -1300.0466 | J27: =-J26*$B$11 -> -1399.2237 | ... N27: =-N26*$B$11 -> -1783.5541 | O27: Tax on EBIT at the statutory rate (unlevered); excludes other income because treasury assets are added in the equity bridge.
A28: NOPAT | C28: =C26+C27 -> 2149.6099 | D28: =D26+D27 -> 2399.2848 | E28: =E26+E27 -> 2718.8159 | F28: =F26+F27 -> 3010.2013 | G28: =G26+G27 -> 3294.747 | H28: =H26+H27 -> 3566.3854 | I28: =I26+I27 -> 3858.8685 | J28: =J26+J27 -> 4153.2513 | ... N28: =N26+N27 -> 5294.0415
A29: Add: D&A | C29: =-C25 -> 313.34 | D29: =-D25 -> 336.83 | E29: =-E25 -> 317.7856 | F29: =-F25 -> 328.77472 | G29: =-G25 -> 342.69014 | H29: =-H25 -> 359.33172 | I29: =-I25 -> 378.48972 | J29: =-J25 -> 400.2351 | ... N29: =-N25 -> 508.29276
A30: Less: capital expenditure | C30: =Model!C63 -> -374.85 | D30: =Model!D63 -> -205.57 | E30: =Model!E63 -> -417.68672 | F30: =Model!F63 -> -455.27853 | G30: =Model!G63 -> -493.9772 | H30: =Model!H63 -> -533.49538 | I30: =Model!I63 -> -576.17501 | J30: =Model!J63 -> -619.38813 | ... N30: =Model!N63 -> -789.3227
A31: Less: increase in net working capital | C31: =-(Model!C50-Model!B50) -> 17.31 | D31: =-(Model!D50-Model!C50) -> -193.08 | E31: =-(Model!E50-Model!D50) -> 24.262144 | F31: =-(Model!F50-Model!E50) -> 40.126669 | G31: =-(Model!G50-Model!F50) -> 41.431543 | H31: =-(Model!H50-Model!G50) -> 42.465628 | I31: =-(Model!I50-Model!H50) -> 45.862879 | J31: =-(Model!J50-Model!I50) -> 46.436165 | ... N31: =-(Model!N50-Model!M50) -> 44.21865 | O31: Britannia runs negative working capital, so growth releases cash (positive number).
A32: Unlevered free cash flow (UFCF) | C32: =C28+C29+C30+C31 -> 2105.4099 | D32: =D28+D29+D30+D31 -> 2337.4648 | E32: =E28+E29+E30+E31 -> 2643.1769 | F32: =F28+F29+F30+F31 -> 2923.8242 | G32: =G28+G29+G30+G31 -> 3184.8914 | H32: =H28+H29+H30+H31 -> 3434.6874 | I32: =I28+I29+I30+I31 -> 3707.046 | J32: =J28+J29+J30+J31 -> 3980.5345 | ... N32: =N28+N29+N30+N31 -> 5057.2302
A34: Forecast year # | E34: 1 | F34: 2 | G34: 3 | H34: 4 | I34: 5 | J34: 6 | K34: 7 | L34: 8 | M34: 9 | N34: 10
A35: Fiscal year-end | E35: =Assumptions!B36 -> 46477 | F35: =DATE(YEAR(E35)+1,3,31) -> 46843 | G35: =DATE(YEAR(F35)+1,3,31) -> 47208 | H35: =DATE(YEAR(G35)+1,3,31) -> 47573 | I35: =DATE(YEAR(H35)+1,3,31) -> 47938 | J35: =DATE(YEAR(I35)+1,3,31) -> 48304 | K35: =DATE(YEAR(J35)+1,3,31) -> 48669 | L35: =DATE(YEAR(K35)+1,3,31) -> 49034 | M35: =DATE(YEAR(L35)+1,3,31) -> 49399 | N35: =DATE(YEAR(M35)+1,3,31) -> 49765
A36: Fraction of year counted | E36: =$B$20 -> 0.44657534 | F36: 1 | G36: 1 | H36: 1 | I36: 1 | J36: 1 | K36: 1 | L36: 1 | M36: 1 | N36: 1
A37: Discount period (years) | E37: =E36*(1-0.5*$B$19) -> 0.22328767 | F37: =$B$20+F34-1+(1-0.5*$B$19) -> 1.9465753 | G37: =$B$20+G34-1+(1-0.5*$B$19) -> 2.9465753 | H37: =$B$20+H34-1+(1-0.5*$B$19) -> 3.9465753 | I37: =$B$20+I34-1+(1-0.5*$B$19) -> 4.9465753 | J37: =$B$20+J34-1+(1-0.5*$B$19) -> 5.9465753 | K37: =$B$20+K34-1+(1-0.5*$B$19) -> 6.9465753 | L37: =$B$20+L34-1+(1-0.5*$B$19) -> 7.9465753 | M37: =$B$20+M34-1+(1-0.5*$B$19) -> 8.9465753 | N37: =$B$20+N34-1+(1-0.5*$B$19) -> 9.9465753 | O37: Mid-year: FY27E stub discounted at half the stub; later years at (stub + n - 1) + 0.5.
A38: Discount factor | E38: =1/(1+$B$17)^E37 -> 0.97825403 | F38: =1/(1+$B$17)^F37 -> 0.82558049 | G38: =1/(1+$B$17)^G37 -> 0.74816407 | H38: =1/(1+$B$17)^H37 -> 0.67800715 | I38: =1/(1+$B$17)^I37 -> 0.61442898 | J38: =1/(1+$B$17)^J37 -> 0.55681268 | K38: =1/(1+$B$17)^K37 -> 0.50459918 | L38: =1/(1+$B$17)^L37 -> 0.45728185 | ... N38: =1/(1+$B$17)^N37 -> 0.37554226
A39: UFCF counted | E39: =E32*E36 -> 1180.3776 | F39: =F32*F36 -> 2923.8242 | G39: =G32*G36 -> 3184.8914 | H39: =H32*H36 -> 3434.6874 | I39: =I32*I36 -> 3707.046 | J39: =J32*J36 -> 3980.5345 | K39: =K32*K36 -> 4255.0909 | L39: =L32*L36 -> 4528.0017 | ... N39: =N32*N36 -> 5057.2302
A40: Present value of UFCF | E40: =E39*E38 -> 1154.7092 | F40: =F39*F38 -> 2413.8522 | G40: =G39*G38 -> 2382.8213 | H40: =H39*H38 -> 2328.7426 | I40: =I39*I38 -> 2277.7165 | J40: =J39*J38 -> 2216.4121 | K40: =K39*K38 -> 2147.1154 | L40: =L39*L38 -> 2070.573 | ... N40: =N39*N38 -> 1899.2036
A42: ENTERPRISE VALUE
A43: Sum of PV of UFCF (FY27E stub - FY36E) | B43: =SUM(E40:N40) -> 20878.775
A44: Terminal-year UFCF x (1 + g) | B44: =N32*(1+B18) -> 5335.3779
A45: Terminal value (Gordon growth) | B45: =B44/(B17-B18) -> 110064.08
A46: PV of terminal value | B46: =B45*N38 -> 41333.712
A47: Enterprise value | B47: =B43+B46 -> 62212.487
A48: Terminal value as % of enterprise value | B48: =B46/B47 -> 0.66439575
A49: Implied terminal EV / EBITDA (on terminal-year EBITDA) | B49: =B45/N24 -> 14.509056
A51: EQUITY BRIDGE (balance sheet as at 31-Mar-2026)
A52: Add: cash and cash equivalents | B52: =Model!D36 -> 220
A53: Add: financial investments (non-current + current) | B53: =Model!D35 -> 3156.23
A54: Add: other treasury assets (bank balances, loans) | B54: =Model!D37 -> 222.44
A55: Add: investment in associates and JV (book value) | B55: =Model!D34 -> 453.53
A56: Less: borrowings incl. lease liabilities | B56: =-Model!D45 -> -1380.28
A57: Less: non-controlling interests (book value) | B57: =-Historical!D59 -> -29.32
A58: Net adjustments (EV to equity) | B58: =SUM(B52:B57) -> 2642.6
A59: Equity value | B59: =B47+B58 -> 64855.087
A60: Shares outstanding (crore) | B60: =Assumptions!$B$39 -> 24.09
A61: DCF value per share (Rs) | B61: =B59/B60 -> 2692.1995
A62: Current share price (Rs) | B62: =Assumptions!$B$37 -> 4764
A63: DCF value vs current price | B63: =B61/B62-1 -> -0.43488675
A65: WHAT THE MARKET PRICE IMPLIES (reverse DCF) AND MULTIPLES
A66: Market enterprise value (Rs crore) | B66: =B13-B58 -> 112122.16
A67: Terminal growth the current price implies (same forecast, same WACC) | B67: =(((B66-B43)/N38)*B17-N32)/(((B66-B43)/N38)+N32) -> 0.080975027 | C67: Solves the Gordon-growth terminal value for g so that DCF value = market price
A68: EV / EBITDA - FY26A (market) | B68: =B66/Model!D14 -> 31.63334
A69: EV / EBITDA - FY27E (market) | B69: =B66/Model!E14 -> 28.366928
A70: EV / EBITDA - FY27E (at DCF value) | B70: =B47/Model!E14 -> 15.739771
A71: P/E - FY26A (market, reported EPS) | B71: =B62/Model!D27 -> 45.293782
A72: P/E - FY27E (market) | B72: =B62/Model!E27 -> 40.791814
A73: P/E - FY27E (at DCF value) | B73: =B61/Model!E27 -> 23.051994

Sheet Sensitivity
A1: Sensitivity analysis
A2: DCF value per share (Rs) - WACC vs terminal growth. Every cell is a live formula (no data table needed).
A4: WACC step | B4: 0.005
A5: Terminal growth step | B5: 0.005
A6: Base WACC | B6: =DCF!B17 -> 0.1034752
A7: Base terminal growth | B7: =DCF!B18 -> 0.055
A9: DCF VALUE PER SHARE (Rs)
A10: WACC (down) / terminal growth (across) | B10: =$B$7+(0-2)*$B$5 -> 0.045 | C10: =$B$7+(1-2)*$B$5 -> 0.05 | D10: =$B$7+(2-2)*$B$5 -> 0.055 | E10: =$B$7+(3-2)*$B$5 -> 0.06 | F10: =$B$7+(4-2)*$B$5 -> 0.065
A11: =$B$6+(0-2)*$B$4 -> 0.093475198 | B11: =(SUMPRODUCT(DCF!$E$39:$N$39/(1+$A11)^DCF!$E$37:$N$37)+DCF!$N$32*(1+B$10)/($A11-B$10)/(1+$A11)^DCF!$N$37+DCF!$B$58)/DCF!$B$60 -> 2881.3387 | C11: =(SUMPRODUCT(DCF!$E$39:$N$39/(1+$A11)^DCF!$E$37:$N$37)+DCF!$N$32*(1+C$10)/($A11-C$10)/(1+$A11)^DCF!$N$37+DCF!$B$58)/DCF!$B$60 -> 3105.2509 | D11: =(SUMPRODUCT(DCF!$E$39:$N$39/(1+$A11)^DCF!$E$37:$N$37)+DCF!$N$32*(1+D$10)/($A11-D$10)/(1+$A11)^DCF!$N$37+DCF!$B$58)/DCF!$B$60 -> 3387.3595 | E11: =(SUMPRODUCT(DCF!$E$39:$N$39/(1+$A11)^DCF!$E$37:$N$37)+DCF!$N$32*(1+E$10)/($A11-E$10)/(1+$A11)^DCF!$N$37+DCF!$B$58)/DCF!$B$60 -> 3753.7421 | F11: =(SUMPRODUCT(DCF!$E$39:$N$39/(1+$A11)^DCF!$E$37:$N$37)+DCF!$N$32*(1+F$10)/($A11-F$10)/(1+$A11)^DCF!$N$37+DCF!$B$58)/DCF!$B$60 -> 4248.792
A12: =$B$6+(1-2)*$B$4 -> 0.098475198 | B12: =(SUMPRODUCT(DCF!$E$39:$N$39/(1+$A12)^DCF!$E$37:$N$37)+DCF!$N$32*(1+B$10)/($A12-B$10)/(1+$A12)^DCF!$N$37+DCF!$B$58)/DCF!$B$60 -> 2609.9807 | C12: =(SUMPRODUCT(DCF!$E$39:$N$39/(1+$A12)^DCF!$E$37:$N$37)+DCF!$N$32*(1+C$10)/($A12-C$10)/(1+$A12)^DCF!$N$37+DCF!$B$58)/DCF!$B$60 -> 2784.7402 | D12: =(SUMPRODUCT(DCF!$E$39:$N$39/(1+$A12)^DCF!$E$37:$N$37)+DCF!$N$32*(1+D$10)/($A12-D$10)/(1+$A12)^DCF!$N$37+DCF!$B$58)/DCF!$B$60 -> 2999.6972 | E12: =(SUMPRODUCT(DCF!$E$39:$N$39/(1+$A12)^DCF!$E$37:$N$37)+DCF!$N$32*(1+E$10)/($A12-E$10)/(1+$A12)^DCF!$N$37+DCF!$B$58)/DCF!$B$60 -> 3270.5233 | F12: =(SUMPRODUCT(DCF!$E$39:$N$39/(1+$A12)^DCF!$E$37:$N$37)+DCF!$N$32*(1+F$10)/($A12-F$10)/(1+$A12)^DCF!$N$37+DCF!$B$58)/DCF!$B$60 -> 3622.2528
A13: =$B$6+(2-2)*$B$4 -> 0.1034752 | B13: =(SUMPRODUCT(DCF!$E$39:$N$39/(1+$A13)^DCF!$E$37:$N$37)+DCF!$N$32*(1+B$10)/($A13-B$10)/(1+$A13)^DCF!$N$37+DCF!$B$58)/DCF!$B$60 -> 2385.2931 | C13: =(SUMPRODUCT(DCF!$E$39:$N$39/(1+$A13)^DCF!$E$37:$N$37)+DCF!$N$32*(1+C$10)/($A13-C$10)/(1+$A13)^DCF!$N$37+DCF!$B$58)/DCF!$B$60 -> 2524.3982 | D13: =(SUMPRODUCT(DCF!$E$39:$N$39/(1+$A13)^DCF!$E$37:$N$37)+DCF!$N$32*(1+D$10)/($A13-D$10)/(1+$A13)^DCF!$N$37+DCF!$B$58)/DCF!$B$60 -> 2692.1995 | E13: =(SUMPRODUCT(DCF!$E$39:$N$39/(1+$A13)^DCF!$E$37:$N$37)+DCF!$N$32*(1+E$10)/($A13-E$10)/(1+$A13)^DCF!$N$37+DCF!$B$58)/DCF!$B$60 -> 2898.5978 | F13: =(SUMPRODUCT(DCF!$E$39:$N$39/(1+$A13)^DCF!$E$37:$N$37)+DCF!$N$32*(1+F$10)/($A13-F$10)/(1+$A13)^DCF!$N$37+DCF!$B$58)/DCF!$B$60 -> 3158.6407
A14: =$B$6+(3-2)*$B$4 -> 0.1084752 | B14: =(SUMPRODUCT(DCF!$E$39:$N$39/(1+$A14)^DCF!$E$37:$N$37)+DCF!$N$32*(1+B$10)/($A14-B$10)/(1+$A14)^DCF!$N$37+DCF!$B$58)/DCF!$B$60 -> 2196.2396 | C14: =(SUMPRODUCT(DCF!$E$39:$N$39/(1+$A14)^DCF!$E$37:$N$37)+DCF!$N$32*(1+C$10)/($A14-C$10)/(1+$A14)^DCF!$N$37+DCF!$B$58)/DCF!$B$60 -> 2308.7845 | D14: =(SUMPRODUCT(DCF!$E$39:$N$39/(1+$A14)^DCF!$E$37:$N$37)+DCF!$N$32*(1+D$10)/($A14-D$10)/(1+$A14)^DCF!$N$37+DCF!$B$58)/DCF!$B$60 -> 2442.3756 | E14: =(SUMPRODUCT(DCF!$E$39:$N$39/(1+$A14)^DCF!$E$37:$N$37)+DCF!$N$32*(1+E$10)/($A14-E$10)/(1+$A14)^DCF!$N$37+DCF!$B$58)/DCF!$B$60 -> 2603.5253 | F14: =(SUMPRODUCT(DCF!$E$39:$N$39/(1+$A14)^DCF!$E$37:$N$37)+DCF!$N$32*(1+F$10)/($A14-F$10)/(1+$A14)^DCF!$N$37+DCF!$B$58)/DCF!$B$60 -> 2801.7421
A15: =$B$6+(4-2)*$B$4 -> 0.1134752 | B15: =(SUMPRODUCT(DCF!$E$39:$N$39/(1+$A15)^DCF!$E$37:$N$37)+DCF!$N$32*(1+B$10)/($A15-B$10)/(1+$A15)^DCF!$N$37+DCF!$B$58)/DCF!$B$60 -> 2035.0077 | C15: =(SUMPRODUCT(DCF!$E$39:$N$39/(1+$A15)^DCF!$E$37:$N$37)+DCF!$N$32*(1+C$10)/($A15-C$10)/(1+$A15)^DCF!$N$37+DCF!$B$58)/DCF!$B$60 -> 2127.3239 | D15: =(SUMPRODUCT(DCF!$E$39:$N$39/(1+$A15)^DCF!$E$37:$N$37)+DCF!$N$32*(1+D$10)/($A15-D$10)/(1+$A15)^DCF!$N$37+DCF!$B$58)/DCF!$B$60 -> 2235.4272 | E15: =(SUMPRODUCT(DCF!$E$39:$N$39/(1+$A15)^DCF!$E$37:$N$37)+DCF!$N$32*(1+E$10)/($A15-E$10)/(1+$A15)^DCF!$N$37+DCF!$B$58)/DCF!$B$60 -> 2363.7461 | F15: =(SUMPRODUCT(DCF!$E$39:$N$39/(1+$A15)^DCF!$E$37:$N$37)+DCF!$N$32*(1+F$10)/($A15-F$10)/(1+$A15)^DCF!$N$37+DCF!$B$58)/DCF!$B$60 -> 2518.5361
A18: UPSIDE / (DOWNSIDE) VS CURRENT PRICE
A19: WACC (down) / terminal growth (across) | B19: =$B$7+(0-2)*$B$5 -> 0.045 | C19: =$B$7+(1-2)*$B$5 -> 0.05 | D19: =$B$7+(2-2)*$B$5 -> 0.055 | E19: =$B$7+(3-2)*$B$5 -> 0.06 | F19: =$B$7+(4-2)*$B$5 -> 0.065
A20: =$B$6+(0-2)*$B$4 -> 0.093475198 | B20: =(SUMPRODUCT(DCF!$E$39:$N$39/(1+$A20)^DCF!$E$37:$N$37)+DCF!$N$32*(1+B$19)/($A20-B$19)/(1+$A20)^DCF!$N$37+DCF!$B$58)/DCF!$B$60/DCF!$B$62-1 -> -0.39518499 | C20: =(SUMPRODUCT(DCF!$E$39:$N$39/(1+$A20)^DCF!$E$37:$N$37)+DCF!$N$32*(1+C$19)/($A20-C$19)/(1+$A20)^DCF!$N$37+DCF!$B$58)/DCF!$B$60/DCF!$B$62-1 -> -0.34818412 | D20: =(SUMPRODUCT(DCF!$E$39:$N$39/(1+$A20)^DCF!$E$37:$N$37)+DCF!$N$32*(1+D$19)/($A20-D$19)/(1+$A20)^DCF!$N$37+DCF!$B$58)/DCF!$B$60/DCF!$B$62-1 -> -0.28896735 | E20: =(SUMPRODUCT(DCF!$E$39:$N$39/(1+$A20)^DCF!$E$37:$N$37)+DCF!$N$32*(1+E$19)/($A20-E$19)/(1+$A20)^DCF!$N$37+DCF!$B$58)/DCF!$B$60/DCF!$B$62-1 -> -0.21206085 | F20: =(SUMPRODUCT(DCF!$E$39:$N$39/(1+$A20)^DCF!$E$37:$N$37)+DCF!$N$32*(1+F$19)/($A20-F$19)/(1+$A20)^DCF!$N$37+DCF!$B$58)/DCF!$B$60/DCF!$B$62-1 -> -0.1081461
A21: =$B$6+(1-2)*$B$4 -> 0.098475198 | B21: =(SUMPRODUCT(DCF!$E$39:$N$39/(1+$A21)^DCF!$E$37:$N$37)+DCF!$N$32*(1+B$19)/($A21-B$19)/(1+$A21)^DCF!$N$37+DCF!$B$58)/DCF!$B$60/DCF!$B$62-1 -> -0.45214511 | C21: =(SUMPRODUCT(DCF!$E$39:$N$39/(1+$A21)^DCF!$E$37:$N$37)+DCF!$N$32*(1+C$19)/($A21-C$19)/(1+$A21)^DCF!$N$37+DCF!$B$58)/DCF!$B$60/DCF!$B$62-1 -> -0.41546175 | D21: =(SUMPRODUCT(DCF!$E$39:$N$39/(1+$A21)^DCF!$E$37:$N$37)+DCF!$N$32*(1+D$19)/($A21-D$19)/(1+$A21)^DCF!$N$37+DCF!$B$58)/DCF!$B$60/DCF!$B$62-1 -> -0.37034063 | E21: =(SUMPRODUCT(DCF!$E$39:$N$39/(1+$A21)^DCF!$E$37:$N$37)+DCF!$N$32*(1+E$19)/($A21-E$19)/(1+$A21)^DCF!$N$37+DCF!$B$58)/DCF!$B$60/DCF!$B$62-1 -> -0.31349218 | F21: =(SUMPRODUCT(DCF!$E$39:$N$39/(1+$A21)^DCF!$E$37:$N$37)+DCF!$N$32*(1+F$19)/($A21-F$19)/(1+$A21)^DCF!$N$37+DCF!$B$58)/DCF!$B$60/DCF!$B$62-1 -> -0.23966146
A22: =$B$6+(2-2)*$B$4 -> 0.1034752 | B22: =(SUMPRODUCT(DCF!$E$39:$N$39/(1+$A22)^DCF!$E$37:$N$37)+DCF!$N$32*(1+B$19)/($A22-B$19)/(1+$A22)^DCF!$N$37+DCF!$B$58)/DCF!$B$60/DCF!$B$62-1 -> -0.49930876 | C22: =(SUMPRODUCT(DCF!$E$39:$N$39/(1+$A22)^DCF!$E$37:$N$37)+DCF!$N$32*(1+C$19)/($A22-C$19)/(1+$A22)^DCF!$N$37+DCF!$B$58)/DCF!$B$60/DCF!$B$62-1 -> -0.47010952 | D22: =(SUMPRODUCT(DCF!$E$39:$N$39/(1+$A22)^DCF!$E$37:$N$37)+DCF!$N$32*(1+D$19)/($A22-D$19)/(1+$A22)^DCF!$N$37+DCF!$B$58)/DCF!$B$60/DCF!$B$62-1 -> -0.43488675 | E22: =(SUMPRODUCT(DCF!$E$39:$N$39/(1+$A22)^DCF!$E$37:$N$37)+DCF!$N$32*(1+E$19)/($A22-E$19)/(1+$A22)^DCF!$N$37+DCF!$B$58)/DCF!$B$60/DCF!$B$62-1 -> -0.39156216 | F22: =(SUMPRODUCT(DCF!$E$39:$N$39/(1+$A22)^DCF!$E$37:$N$37)+DCF!$N$32*(1+F$19)/($A22-F$19)/(1+$A22)^DCF!$N$37+DCF!$B$58)/DCF!$B$60/DCF!$B$62-1 -> -0.33697719
A23: =$B$6+(3-2)*$B$4 -> 0.1084752 | B23: =(SUMPRODUCT(DCF!$E$39:$N$39/(1+$A23)^DCF!$E$37:$N$37)+DCF!$N$32*(1+B$19)/($A23-B$19)/(1+$A23)^DCF!$N$37+DCF!$B$58)/DCF!$B$60/DCF!$B$62-1 -> -0.53899252 | C23: =(SUMPRODUCT(DCF!$E$39:$N$39/(1+$A23)^DCF!$E$37:$N$37)+DCF!$N$32*(1+C$19)/($A23-C$19)/(1+$A23)^DCF!$N$37+DCF!$B$58)/DCF!$B$60/DCF!$B$62-1 -> -0.51536849 | D23: =(SUMPRODUCT(DCF!$E$39:$N$39/(1+$A23)^DCF!$E$37:$N$37)+DCF!$N$32*(1+D$19)/($A23-D$19)/(1+$A23)^DCF!$N$37+DCF!$B$58)/DCF!$B$60/DCF!$B$62-1 -> -0.4873267 | E23: =(SUMPRODUCT(DCF!$E$39:$N$39/(1+$A23)^DCF!$E$37:$N$37)+DCF!$N$32*(1+E$19)/($A23-E$19)/(1+$A23)^DCF!$N$37+DCF!$B$58)/DCF!$B$60/DCF!$B$62-1 -> -0.45350014 | F23: =(SUMPRODUCT(DCF!$E$39:$N$39/(1+$A23)^DCF!$E$37:$N$37)+DCF!$N$32*(1+F$19)/($A23-F$19)/(1+$A23)^DCF!$N$37+DCF!$B$58)/DCF!$B$60/DCF!$B$62-1 -> -0.41189293
A24: =$B$6+(4-2)*$B$4 -> 0.1134752 | B24: =(SUMPRODUCT(DCF!$E$39:$N$39/(1+$A24)^DCF!$E$37:$N$37)+DCF!$N$32*(1+B$19)/($A24-B$19)/(1+$A24)^DCF!$N$37+DCF!$B$58)/DCF!$B$60/DCF!$B$62-1 -> -0.57283633 | C24: =(SUMPRODUCT(DCF!$E$39:$N$39/(1+$A24)^DCF!$E$37:$N$37)+DCF!$N$32*(1+C$19)/($A24-C$19)/(1+$A24)^DCF!$N$37+DCF!$B$58)/DCF!$B$60/DCF!$B$62-1 -> -0.55345847 | D24: =(SUMPRODUCT(DCF!$E$39:$N$39/(1+$A24)^DCF!$E$37:$N$37)+DCF!$N$32*(1+D$19)/($A24-D$19)/(1+$A24)^DCF!$N$37+DCF!$B$58)/DCF!$B$60/DCF!$B$62-1 -> -0.53076675 | E24: =(SUMPRODUCT(DCF!$E$39:$N$39/(1+$A24)^DCF!$E$37:$N$37)+DCF!$N$32*(1+E$19)/($A24-E$19)/(1+$A24)^DCF!$N$37+DCF!$B$58)/DCF!$B$60/DCF!$B$62-1 -> -0.50383162 | F24: =(SUMPRODUCT(DCF!$E$39:$N$39/(1+$A24)^DCF!$E$37:$N$37)+DCF!$N$32*(1+F$19)/($A24-F$19)/(1+$A24)^DCF!$N$37+DCF!$B$58)/DCF!$B$60/DCF!$B$62-1 -> -0.47134002
A27: Check: centre cell equals DCF sheet value per share | B27: =IF(ABS(D13-DCF!B61)<0.5,"OK","ERROR") -> OK
A28: Inner range (WACC +/- 1 step, g +/- 1 step): low | B28: =MIN(C12:E14) -> 2308.7845
A29: Inner range: high | B29: =MAX(C12:E14) -> 3270.5233

Sheet Comps
A1: Trading comparables (indicative cross-check)
A2: Same-date peer snapshot so multiples are comparable. Refresh every figure before presenting.
A4: Company | B4: Mkt cap (Rs cr) | C4: P/E (TTM) | D4: P/B | E4: ROE | F4: EPS TTM (Rs) | G4: Source / date
A5: Hindustan Unilever | B5: 503929 | C5: 32.12 | D5: 9.91 | E5: 0.3107 | F5: 65.66 | G5: Upstox peer table, page dated 27-Jul-2026
A6: Varun Beverages | B6: 154680 | C6: 52.65 | D6: 8.59 | E6: 0.1551 | F6: 7.91 | G6: Upstox peer table, page dated 27-Jul-2026
A7: Marico | B7: 111116 | C7: 54.34 | D7: 22.74 | E7: 0.443 | F7: 15 | G7: Upstox peer table, page dated 27-Jul-2026
A8: Godrej Consumer Products | B8: 108388 | C8: 54.13 | D8: 7.97 | E8: 0.151 | F8: 14.81 | G8: Upstox peer table, page dated 27-Jul-2026
A9: Peer median | C9: =MEDIAN(C5:C8) -> 53.39 | D9: =MEDIAN(D5:D8) -> 9.25 | E9: =MEDIAN(E5:E8) -> 0.2329
A10: Peer mean | C10: =AVERAGE(C5:C8) -> 48.31 | D10: =AVERAGE(D5:D8) -> 12.3025 | E10: =AVERAGE(E5:E8) -> 0.26495
A11: Peer high | C11: =MAX(C5:C8) -> 54.34 | D11: =MAX(D5:D8) -> 22.74 | E11: =MAX(E5:E8) -> 0.443
A12: Peer low | C12: =MIN(C5:C8) -> 32.12 | D12: =MIN(D5:D8) -> 7.97 | E12: =MIN(E5:E8) -> 0.151
A14: Britannia (same 27-Jul-2026 snapshot) | B14: 129677 | C14: 51.6 | D14: 25.6 | E14: 0.5362 | F14: 106.35 | G14: Upstox peer table, page dated 27-Jul-2026
A15: Britannia (current) | B15: =DCF!B13 -> 114764.76 | C15: =Assumptions!$B$37/Assumptions!$B$46 -> 44.066229 | E15: 0.535 | F15: =Assumptions!$B$46 -> 108.11 | G15: Screener.in 16-Oct-2026 (price Rs 4,764; TTM EPS Rs 108.11; ROE 53.5%)
A17: IMPLIED BRITANNIA VALUE FROM PEER P/E (x Britannia TTM EPS)
B18: Low | C18: Median | D18: High
A19: Peer P/E (x) | B19: =C12 -> 32.12 | C19: =C9 -> 53.39 | D19: =C11 -> 54.34
A20: Implied value per share (Rs) | B20: =B19*Assumptions!$B$46 -> 3472.4932 | C20: =C19*Assumptions!$B$46 -> 5771.9929 | D20: =D19*Assumptions!$B$46 -> 5874.6974
A21: vs current price | B21: =B20/Assumptions!$B$37-1 -> -0.27109715 | C21: =C20/Assumptions!$B$37-1 -> 0.21158541 | D21: =D20/Assumptions!$B$37-1 -> 0.23314387
A23: Notes
A24: Peers were chosen from the one page that gave all companies on the same date; Nestle India, ITC, Tata Consumer and Dabur are not included because a consistent same-date source was not found.
A25: Britannia has de-rated since the snapshot (P/E 51.6x on 27-Jul-2026 vs 44.1x on 16-Oct-2026), so peer multiples from July are stale relative to the current price. Refresh before relying on this.
A26: P/E-only comps are a rough cross-check; add EV/EBITDA once peer EBITDA and net debt are sourced on the same date.
